komoe/__init__.py
komoe/__main__.py
komoe/builder.py
komoe/commands.py
komoe/config.py
komoe/context.py
komoe/doctree.py
komoe/log.py
komoe/main.py
komoe/markdown.py
komoe/plugin.py
komoe/relationships.py
komoe/snapshot.py
komoe/template.py
komoe/utils.py
komoe/version.py
Komoe-0.4.0.dist-info/METADATA
Komoe-0.4.0.dist-info/WHEEL
Komoe-0.4.0.dist-info/entry_points.txt
Komoe-0.4.0.dist-info/top_level.txt
Komoe-0.4.0.dist-info/RECORD
