Metadata-Version: 2.1
Name: Komoe
Version: 0.4.0
Summary: A static site generator
Home-page: https://github.com/louisdevie/komoe
Author: Louis DEVIE
License: MIT License
Keywords: static,site,website,template,templating
Platform: UNKNOWN
Classifier: Development Status :: 4 - Beta
Classifier: License :: OSI Approved :: MIT License
Classifier: Programming Language :: Python :: 3.8
Requires-Python: >=3.8
Requires-Dist: Jinja2-TD (==3.1-post2)
Requires-Dist: Jinja2 (==3.1.2)
Requires-Dist: Markdown (==3.4.1)
Requires-Dist: click (>=8.1.3)
Requires-Dist: tomli (>=2.0.1)
Requires-Dist: watchfiles (>=0.18.1)
